{"Boston Red Sox":{"team":"Boston Red Sox","ticket":"53.38","premium ticket":"172.51","beer":"7.25","soda":"4.00","hotDog":"4.50","parking":"27.00","program":"5.00","cap":"18.99","FCI":"336.99"},"New York Yankees":{"team":"New York Yankees","ticket":"51.55","change":"-0.3","premium ticket":"305.11","beer":"6.00","soda":"3.00","hotDog":"3.00","parking":"35.00","program":"5.00","cap":"25.00","FCI":"324.30"},"Chicago Cubs":{"team":"Chicago Cubs","ticket":"46.30","premium ticket":"103.98","beer":"7.00","soda":"4.00","hotDog":"5.00","parking":"25.00","program":"5.00","cap":"15.00","FCI":"300.29"},"Philadelphia Phillies":{"team":"Philadelphia Phillies","ticket":"37.42","premium ticket":"79.82","beer":"7.75","soda":"4.00","hotDog":"3.75","parking":"15.00","program":"5.00","cap":"17.99","FCI":"257.16"},"Miami Marlins":{"team":"Miami Marlins","ticket":"29.62","premium ticket":"195.81","beer":"8.00","soda":"4.50","hotDog":"6.00","parking":"15.00","program":"5.00","cap":"19.99","FCI":"242.47"},"Detroit Tigers":{"team":"Detroit Tigers","ticket":"31.00","premium ticket":"76.88","beer":"6.75","soda":"4.25","hotDog":"5.50","parking":"5.00","program":"5.00","cap":"20.99","FCI":"233.49"},"New York Mets":{"team":"New York Mets","ticket":"27.24","change":"-4.7","premium ticket":"91.76","beer":"5.75","soda":"4.50","hotDog":"6.00","parking":"20.00","program":"5.00","cap":"18.99","FCI":"230.44"},"Minnesota Twins":{"team":"Minnesota Twins","ticket":"33.04","premium ticket":"71.08","beer":"7.00","soda":"4.00","hotDog":"3.75","parking":"6.00","program":"3.00","cap":"17.99","FCI":"225.14"},"St. Louis Cardinals":{"team":"St. Louis Cardinals","ticket":"31.57","premium ticket":"73.97","beer":"6.75","soda":"5.25","hotDog":"4.25","parking":"10.00","program":"2.50","cap":"15.99","FCI":"224.76"},"Houston Astros":{"team":"Houston Astros","ticket":"30.09","premium ticket":"51.24","beer":"5.00","soda":"4.50","hotDog":"4.75","parking":"15.00","program":"4.00","cap":"16.99","FCI":"224.33"},"San Francisco Giants":{"team":"San Francisco Giants","ticket":"27.21","premium ticket":"82.45","beer":"6.25","soda":"4.25","hotDog":"5.00","parking":"20.00","program":"5.00","cap":"17.99","FCI":"224.32"},"Chicago White Sox":{"team":"Chicago White Sox","ticket":"29.00","change":"-13.8","premium ticket":"90.97","beer":"6.50","soda":"3.00","hotDog":"3.75","parking":"23.00","program":"4.00","cap":"17.99","FCI":"222.98"},"Toronto Blue Jays":{"team":"Toronto Blue Jays","ticket":"24.81","premium ticket":"58.52","beer":"7.19","soda":"4.96","hotDog":"5.20","parking":"14.87","program":"4.96","cap":"18.92","FCI":"216.89"},"Los Angeles Dodgers":{"team":"Los Angeles Dodgers","ticket":"23.22","change":"-9.7","premium ticket":"222.38","beer":"6.25","soda":"5.25","hotDog":"5.00","parking":"15.00","program":"5.00","cap":"20.99","FCI":"213.36"},"Washington Nationals":{"team":"Washington Nationals","ticket":"30.54","premium ticket":"166.25","beer":"6.50","soda":"4.50","hotDog":"4.50","parking":"5.00","program":"0.00","cap":"10.00","FCI":"198.16"},"Seattle Mariners":{"team":"Seattle Mariners","ticket":"26.40","premium ticket":"56.98","beer":"5.50","soda":"2.50","hotDog":"3.50","parking":"17.00","program":"3.00","cap":"15.99","FCI":"195.57"},"Oakland Athletics":{"team":"Oakland Athletics","ticket":"21.64","premium ticket":"46.28","beer":"5.00","soda":"2.75","hotDog":"3.50","parking":"17.00","program":"5.00","cap":"18.99","FCI":"186.55"},"Kansas City Royals":{"team":"Kansas City Royals","ticket":"21.84","premium ticket":"92.38","beer":"6.00","soda":"4.00","hotDog":"4.00","parking":"6.00","program":"5.00","cap":"18.99","FCI":"185.33"},"Colorado Rockies":{"team":"Colorado Rockies","ticket":"20.55","premium ticket":"38.00","beer":"6.00","soda":"3.25","hotDog":"4.75","parking":"8.00","program":"5.00","cap":"20.00","FCI":"184.20"},"Texas Rangers":{"team":"Texas Rangers","ticket":"20.49","premium ticket":"50.20","beer":"6.50","soda":"3.50","hotDog":"4.75","parking":"10.00","program":"5.00","cap":"17.99","FCI":"183.93"},"Baltimore Orioles":{"team":"Baltimore Orioles","ticket":"23.89","premium ticket":"43.90","beer":"6.25","soda":"2.00","hotDog":"2.50","parking":"8.00","program":"5.00","cap":"15.99","FCI":"176.04"},"Cleveland Indians":{"team":"Cleveland Indians","ticket":"20.42","premium ticket":"65.93","beer":"5.50","soda":"5.00","hotDog":"4.25","parking":"12.00","program":"0.00","cap":"15.99","FCI":"173.66"},"Atlanta Braves":{"team":"Atlanta Braves","ticket":"16.69","change":"-4.1","premium ticket":"43.46","beer":"7.00","soda":"4.50","hotDog":"4.50","parking":"15.00","program":"0.00","cap":"19.99","FCI":"171.74"},"Milwaukee Brewers":{"team":"Milwaukee Brewers","ticket":"24.01","premium ticket":"42.53","beer":"5.75","soda":"2.50","hotDog":"3.25","parking":"9.00","program":"0.00","cap":"15.99","FCI":"171.52"},"Cincinnati Reds":{"team":"Cincinnati Reds","ticket":"20.49","premium ticket":"59.56","beer":"5.50","soda":"1.00","hotDog":"1.00","parking":"17.00","program":"4.00","cap":"19.99","FCI":"165.94"},"Los Angeles Angels":{"team":"Los Angeles Angels","ticket":"19.71","premium ticket":"74.21","beer":"4.50","soda":"3.00","hotDog":"3.00","parking":"10.00","program":"3.00","cap":"15.99","FCI":"159.82"},"Tampa Bay Rays":{"team":"Tampa Bay Rays","ticket":"19.83","premium ticket":"82.31","beer":"5.00","soda":"2.00","hotDog":"5.00","parking":"0.00","program":"0.00","cap":"17.99","FCI":"153.30"},"Pittsburgh Pirates":{"team":"Pittsburgh Pirates","ticket":"11","premium ticket":"49.38","beer":"5.00","soda":"3.00","hotDog":"3.00","parking":"10.00","program":"0.00","cap":"21.99","FCI":"152.41"},"San Diego Padres":{"team":"San Diego Padres","ticket":"15.67","premium ticket":"37.83","beer":"5.00","soda":"4.00","hotDog":"4.00","parking":"8.00","program":"0.00","cap":"18.99","FCI":"150.66"},"Arizona Diamondbacks":{"team":"Arizona Diamondbacks","ticket":"15.74","premium ticket":"58.28","beer":"4.00","soda":"4.00","hotDog":"2.75","parking":"10.00","program":"0.00","cap":"18.99","FCI":"145.94"}}